BobrTools/__init__.py
BobrTools/db_connectors.py
BobrTools/google_docs.py
BobrTools/helpers.py
BobrTools/slack_client.py
BobrTools/telegram_client.py
bobrtools-0.1.32.dist-info/METADATA
bobrtools-0.1.32.dist-info/WHEEL
bobrtools-0.1.32.dist-info/top_level.txt
bobrtools-0.1.32.dist-info/RECORD
