Metadata-Version: 2.4
Name: BobrTools
Version: 0.1.32
Summary: Tools designed to simplify routine tasks for analysts, enabling faster and more efficient data processing and analysis
Author: Artsem Bobr
Author-email: artyombobr@gmail.com
License: MIT
Classifier: Programming Language :: Python :: 3
Classifier: License :: OSI Approved :: MIT License
Classifier: Operating System :: OS Independent
Requires-Python: >=3.8
Requires-Dist: gspread==6.1.4
Requires-Dist: gspread_formatting==1.2.0
Requires-Dist: oauth2client==4.1.3
Requires-Dist: pandas>=2.1
Requires-Dist: numpy>=1.26
Requires-Dist: slack-sdk==3.34.0
Requires-Dist: python-telegram-bot==21.6
Requires-Dist: snowflake-connector-python[pandas]==3.12.4
Requires-Dist: PySocks==1.7.1
Requires-Dist: tenacity==9.0.0
Requires-Dist: sqlalchemy==2.0.39
Requires-Dist: mysql-connector-python==8.3.0
Requires-Dist: certifi==2025.1.31
Requires-Dist: pyOpenSSL==23.2.0
Dynamic: author
Dynamic: author-email
Dynamic: classifier
Dynamic: description
Dynamic: description-content-type
Dynamic: license
Dynamic: requires-dist
Dynamic: requires-python
Dynamic: summary
